pssm/__init__.py
pssm/cli.py
pssm/core.py
pssm/env.py
pssm/sep/io.py
pssm/sep/system.py
pssm/sep/term.py
pssm/setup.py
pssm/validate/service.py
python_simple_secrets_manager-0.1.1.dist-info/LICENSE
python_simple_secrets_manager-0.1.1.dist-info/METADATA
python_simple_secrets_manager-0.1.1.dist-info/WHEEL
python_simple_secrets_manager-0.1.1.dist-info/entry_points.txt
python_simple_secrets_manager-0.1.1.dist-info/RECORD
